Metadata-Version: 2.4
Name: discord-mcp
Version: 0.1.5
Summary: Discord Message Context Provider for Claude
Home-page: https://github.com/LouD82/discord-mcp
Author: Louis DiLello
Author-email: Louis DiLello <discord-mcp@example.com>
License: MIT
Project-URL: Homepage, https://github.com/LouD82/discord-mcp
Project-URL: Bug Tracker, https://github.com/LouD82/discord-mcp/issues
Classifier: Development Status :: 4 - Beta
Classifier: Intended Audience :: Developers
Classifier: License :: OSI Approved :: MIT License
Classifier: Programming Language :: Python :: 3
Classifier: Programming Language :: Python :: 3.10
Classifier: Topic :: Communications :: Chat
Classifier: Topic :: Utilities
Requires-Python: >=3.10
License-File: LICENSE
Requires-Dist: mcp[cli]>=0.1.0
Requires-Dist: bm25s>=0.2.10
Requires-Dist: numpy>=1.24.0
Requires-Dist: tqdm>=4.66.1
Requires-Dist: requests>=2.31.0
Requires-Dist: pytz>=2023.3
Requires-Dist: flask>=2.3.0
Requires-Dist: python-dotenv>=1.0.0
Dynamic: author
Dynamic: home-page
Dynamic: license-file
Dynamic: requires-python
